{"0": {"length": 2, "0": "Gran", "1": "Djeeta"}, "1": {"0": {"wpn": "1010400400", "cjs": ["wrk_wa_0_01"], "action_label_list": ["ability", "mortal_A", "stbwait", "short_attack", "double", "triple"], "effect": ["phit_wa_0001"], "special": [{"random": 0, "list": [{"target": "them", "cjs": "sp_wa_01210001", "fixed_pos_owner_bg": 0, "full_screen": 0}]}], "cjs_pos": [{"y": 0, "x": 0}], "special_pos": [[{"y": 0, "x": 0}]]}, "1": {"wpn": "1010400400", "cjs": ["wrk_wa_1_01"], "action_label_list": ["ability", "mortal_A", "stbwait", "short_attack", "double", "triple"], "effect": ["phit_wa_0001"], "special": [{"random": 0, "list": [{"target": "them", "cjs": "sp_wa_01210001", "fixed_pos_owner_bg": 0, "full_screen": 0}]}], "cjs_pos": [{"y": 0, "x": 0}], "special_pos": [[{"y": 0, "x": 0}]]}}, "2": {"1": {"1": ""}, "2": {"1": ""}}}